colapy/__init__.py
colapy/__init__.pyi
colapy/_cola_impl.cpython-312-darwin.so
colapy-0.0.1.2.dist-info/METADATA
colapy-0.0.1.2.dist-info/WHEEL
colapy-0.0.1.2.dist-info/licenses/LICENSE
colapy-0.0.1.2.dist-info/RECORD
